uharfbuzz/__init__.py
uharfbuzz/_harfbuzz.abi3.so
uharfbuzz/_harfbuzz_test.abi3.so
uharfbuzz/_version.py
uharfbuzz.libs/libgcc_s-0cd532bd.so.1
uharfbuzz.libs/libstdc++-5d72f927.so.6.0.33
uharfbuzz-0.53.2.dist-info/METADATA
uharfbuzz-0.53.2.dist-info/WHEEL
uharfbuzz-0.53.2.dist-info/top_level.txt
uharfbuzz-0.53.2.dist-info/RECORD
uharfbuzz-0.53.2.dist-info/licenses/LICENSE
uharfbuzz-0.53.2.dist-info/sboms/auditwheel.cdx.json
