Metadata-Version: 2.4
Name: uharfbuzz
Version: 0.53.2
Summary: Streamlined Cython bindings for the harfbuzz shaping engine
Home-page: https://github.com/trufont/uharfbuzz
Author: Adrien Tétar
Author-email: adri-from-59@hotmail.fr
License: Apache License 2.0
Requires-Python: >=3.10
License-File: LICENSE
Dynamic: author
Dynamic: author-email
Dynamic: description
Dynamic: description-content-type
Dynamic: home-page
Dynamic: license
Dynamic: license-file
Dynamic: requires-python
Dynamic: summary
